slack_logging/__init__.py
slack_logging/configuration.py
slack_logging/formatters.py
slack_logging/handlers.py
slack_logging/integrations.py
slack_logging-1.0.2.dist-info/METADATA
slack_logging-1.0.2.dist-info/RECORD
slack_logging-1.0.2.dist-info/WHEEL
slack_logging-1.0.2.dist-info/top_level.txt
