Metadata-Version: 2.1
Name: slack-logging
Version: 1.0.2
Summary: Python2 logger/handler for slack integration
Home-page: https://github.com/iotgdev/slack_logging/
Author: iotec
Author-email: dev@dsp.io
License: UNKNOWN
Download-URL: https://github.com/iotgdev/slack_logging/archive/1.0.2.tar.gz
Platform: UNKNOWN
Requires-Dist: requests (>=2.19.1)
Requires-Dist: ujson (>=1.35)
